rtl/common/handshake_fifo.sv
// =====================================================================
// handshake_fifo.sv  --  Generic synchronous valid/ready FIFO
// ---------------------------------------------------------------------
// Simple circular-buffer FIFO with standard valid/ready handshakes on
// both ends.
//
// Producer side (in_*):
//   - Writes complete on cycles where (in_valid && in_ready) is high
//     at the rising edge.
//   - in_ready is high iff the FIFO is not full.
//
// Consumer side (out_*):
//   - Reads complete on cycles where (out_valid && out_ready) is high.
//   - out_valid is high iff the FIFO is not empty.
//   - out_data is the head entry (combinational read of mem[rd_ptr]).
//
// Sizing:
//   - DEPTH must be a power of 2 (we use a (clog2(DEPTH)+1)-bit pointer
//     pair to distinguish full from empty).
//
// Concurrent in+out at the same cycle is supported. Reset clears both
// pointers; mem contents are don't-care.
// =====================================================================

`ifndef HANDSHAKE_FIFO_SV
`define HANDSHAKE_FIFO_SV

module handshake_fifo #(
    parameter int WIDTH = 8,
    parameter int DEPTH = 16   // must be a power of 2
) (
    input  logic              clk,
    input  logic              rst_n,

    // Producer
    input  logic              in_valid,
    output logic              in_ready,
    input  logic [WIDTH-1:0]  in_data,

    // Consumer
    output logic              out_valid,
    input  logic              out_ready,
    output logic [WIDTH-1:0]  out_data
);

    localparam int IDX_W = $clog2(DEPTH);

    logic [WIDTH-1:0] mem [DEPTH];

    // (IDX_W+1)-bit pointers: the lower IDX_W bits are the memory
    // address, the top bit is a wrap-parity tag so that
    //   wr == rd                  -> empty
    //   wr[low]==rd[low] and wr[top]!=rd[top] -> full
    logic [IDX_W:0] wr_ptr_q;
    logic [IDX_W:0] rd_ptr_q;

    logic empty, full;
    assign empty = (wr_ptr_q == rd_ptr_q);
    assign full  = (wr_ptr_q[IDX_W-1:0] == rd_ptr_q[IDX_W-1:0])
                && (wr_ptr_q[IDX_W]     != rd_ptr_q[IDX_W]);

    // Concurrent read forwards capacity to the producer in the same
    // cycle: when full but the consumer is also reading, in_ready
    // still goes high so the next entry can land.
    logic do_rd;
    assign do_rd = !empty && out_ready;

    assign in_ready  = !full || do_rd;
    assign out_valid = !empty;
    assign out_data  = mem[rd_ptr_q[IDX_W-1:0]];

    logic do_wr;
    assign do_wr = in_valid && in_ready;

    always_ff @(posedge clk or negedge rst_n) begin
        if (!rst_n) begin
            wr_ptr_q <= '0;
            rd_ptr_q <= '0;
        end else begin
            if (do_wr) begin
                mem[wr_ptr_q[IDX_W-1:0]] <= in_data;
                wr_ptr_q <= wr_ptr_q + 1'b1;
            end
            if (do_rd) begin
                rd_ptr_q <= rd_ptr_q + 1'b1;
            end
        end
    end

endmodule

`endif  // HANDSHAKE_FIFO_SV

sim/waves/handshake_fifo.vcd
$version Generated by VerilatedVcd $end
$timescale 1ps $end
 $scope module TOP $end
  $var wire 1 6 clk $end
  $var wire 1 7 rst_n $end
  $var wire 1 8 in_valid $end
  $var wire 1 9 in_ready $end
  $var wire 8 : in_data [7:0] $end
  $var wire 1 ; out_valid $end
  $var wire 1 < out_ready $end
  $var wire 8 = out_data [7:0] $end
  $scope module handshake_fifo $end
   $var wire 32 @ WIDTH [31:0] $end
   $var wire 32 A DEPTH [31:0] $end
   $var wire 1 6 clk $end
   $var wire 1 7 rst_n $end
   $var wire 1 8 in_valid $end
   $var wire 1 9 in_ready $end
   $var wire 8 : in_data [7:0] $end
   $var wire 1 ; out_valid $end
   $var wire 1 < out_ready $end
   $var wire 8 = out_data [7:0] $end
   $var wire 32 B IDX_W [31:0] $end
   $var wire 8 " mem[0] [7:0] $end
   $var wire 8 # mem[1] [7:0] $end
   $var wire 8 $ mem[2] [7:0] $end
   $var wire 8 % mem[3] [7:0] $end
   $var wire 8 & mem[4] [7:0] $end
   $var wire 8 ' mem[5] [7:0] $end
   $var wire 8 ( mem[6] [7:0] $end
   $var wire 8 ) mem[7] [7:0] $end
   $var wire 8 * mem[8] [7:0] $end
   $var wire 8 + mem[9] [7:0] $end
   $var wire 8 , mem[10] [7:0] $end
   $var wire 8 - mem[11] [7:0] $end
   $var wire 8 . mem[12] [7:0] $end
   $var wire 8 / mem[13] [7:0] $end
   $var wire 8 0 mem[14] [7:0] $end
   $var wire 8 1 mem[15] [7:0] $end
   $var wire 5 2 wr_ptr_q [4:0] $end
   $var wire 5 3 rd_ptr_q [4:0] $end
   $var wire 1 4 empty $end
   $var wire 1 5 full $end
   $var wire 1 > do_rd $end
   $var wire 1 ? do_wr $end
  $upscope $end
 $upscope $end
$enddefinitions $end


#0
b00000000 "
b00000000 #
b00000000 $
b00000000 %
b00000000 &
b00000000 '
b00000000 (
b00000000 )
b00000000 *
b00000000 +
b00000000 ,
b00000000 -
b00000000 .
b00000000 /
b00000000 0
b00000000 1
b00000 2
b00000 3
14
05
06
07
08
19
b00000000 :
0;
0<
b00000000 =
0>
0?
b00000000000000000000000000001000 @
b00000000000000000000000000010000 A
b00000000000000000000000000000100 B
#5
16
#10
06
#15
16
#20
06
#25
16
#30
06
#35
16
#40
06
17
#45
16
#50
06
07
#55
16
#60
06
#65
16
#70
06
#75
16
#80
06
#85
16
#90
06
17
#95
16
#100
06
18
b01000010 :
1?
#105
b01000010 "
b00001 2
04
16
1;
b01000010 =
#110
06
08
b00000000 :
1<
1>
0?
#115
b00001 3
14
16
0;
b00000000 =
0>
#120
b00000 2
b00000 3
06
07
0<
b01000010 =
#125
16
#130
06
#135
16
#140
06
#145
16
#150
06
#155
16
#160
06
17
#165
16
#170
06
18
b10101010 :
1?
#175
b10101010 "
b00001 2
04
16
1;
b10101010 =
#180
06
b10111011 :
#185
b10111011 #
b00010 2
16
#190
06
b11001100 :
#195
b11001100 $
b00011 2
16
#200
06
08
b00000000 :
1<
1>
0?
#205
b00001 3
16
b10111011 =
#210
06
#215
b00010 3
16
b11001100 =
#220
06
#225
b00011 3
14
16
0;
b00000000 =
0>
#230
b00000 2
b00000 3
06
07
0<
b10101010 =
#235
16
#240
06
#245
16
#250
06
#255
16
#260
06
#265
16
#270
06
17
#275
16
#280
06
18
b00000001 :
1?
#285
b00000001 "
b00001 2
04
16
1;
b00000001 =
#290
06
b00000010 :
#295
b00000010 #
b00010 2
16
#300
06
b00000011 :
#305
b00000011 $
b00011 2
16
#310
06
b00000100 :
#315
b00000100 %
b00100 2
16
#320
06
b00000101 :
#325
b00000101 &
b00101 2
16
#330
06
b00000110 :
#335
b00000110 '
b00110 2
16
#340
06
b00000111 :
#345
b00000111 (
b00111 2
16
#350
06
b00001000 :
#355
b00001000 )
b01000 2
16
#360
06
b00001001 :
#365
b00001001 *
b01001 2
16
#370
06
b00001010 :
#375
b00001010 +
b01010 2
16
#380
06
b00001011 :
#385
b00001011 ,
b01011 2
16
#390
06
b00001100 :
#395
b00001100 -
b01100 2
16
#400
06
b00001101 :
#405
b00001101 .
b01101 2
16
#410
06
b00001110 :
#415
b00001110 /
b01110 2
16
#420
06
b00001111 :
#425
b00001111 0
b01111 2
16
#430
06
b00010000 :
#435
b00010000 1
b10000 2
15
16
09
0?
#440
06
b11111111 :
#445
16
#450
06
08
19
b00000000 :
1<
1>
#455
b00001 3
05
16
b00000010 =
#460
06
#465
b00010 3
16
b00000011 =
#470
06
#475
b00011 3
16
b00000100 =
#480
06
#485
b00100 3
16
b00000101 =
#490
06
#495
b00101 3
16
b00000110 =
#500
06
#505
b00110 3
16
b00000111 =
#510
06
#515
b00111 3
16
b00001000 =
#520
06
#525
b01000 3
16
b00001001 =
#530
06
#535
b01001 3
16
b00001010 =
#540
06
#545
b01010 3
16
b00001011 =
#550
06
#555
b01011 3
16
b00001100 =
#560
06
#565
b01100 3
16
b00001101 =
#570
06
#575
b01101 3
16
b00001110 =
#580
06
#585
b01110 3
16
b00001111 =
#590
06
#595
b01111 3
16
b00010000 =
#600
06
#605
b10000 3
14
16
0;
b00000001 =
0>
#610
b00000 2
b00000 3
06
07
0<
#615
16
#620
06
#625
16
#630
06
#635
16
#640
06
#645
16
#650
06
17
#655
16
#660
06
18
b01010101 :
1?
#665
b01010101 "
b00001 2
04
16
1;
b01010101 =
#670
06
b01100110 :
#675
b01100110 #
b00010 2
16
#680
06
08
b00000000 :
1<
1>
0?
#685
b00001 3
16
b01100110 =
#690
06
#695
b00010 3
14
16
0;
b00000011 =
0>
#700
b00000 2
b00000 3
06
07
0<
b01010101 =
#705
16
#710
06
#715
16
#720
06
#725
16
#730
06
#735
16
#740
06
17
#745
16
#750
06
18
1?
#755
b00000000 "
b00001 2
04
16
1;
b00000000 =
#760
06
b00000001 :
#765
b00000001 #
b00010 2
16
#770
06
b00000010 :
#775
b00000010 $
b00011 2
16
#780
06
b00000011 :
#785
b00000011 %
b00100 2
16
#790
06
b00000100 :
#795
b00000100 &
b00101 2
16
#800
06
b00000101 :
#805
b00000101 '
b00110 2
16
#810
06
b00000110 :
#815
b00000110 (
b00111 2
16
#820
06
b00000111 :
#825
b00000111 )
b01000 2
16
#830
06
b00001000 :
#835
b00001000 *
b01001 2
16
#840
06
b00001001 :
#845
b00001001 +
b01010 2
16
#850
06
b00001010 :
#855
b00001010 ,
b01011 2
16
#860
06
b00001011 :
#865
b00001011 -
b01100 2
16
#870
06
b00001100 :
#875
b00001100 .
b01101 2
16
#880
06
b00001101 :
#885
b00001101 /
b01110 2
16
#890
06
b00001110 :
#895
b00001110 0
b01111 2
16
#900
06
b00001111 :
#905
b00001111 1
b10000 2
15
16
09
0?
#910
06
19
b10101010 :
1<
1>
1?
#915
b10101010 "
b10001 2
b00001 3
16
b00000001 =
#920
06
08
b00000000 :
0?
#925
b00010 3
05
16
b00000010 =
#930
06
#935
b00011 3
16
b00000011 =
#940
06
#945
b00100 3
16
b00000100 =
#950
06
#955
b00101 3
16
b00000101 =
#960
06
#965
b00110 3
16
b00000110 =
#970
06
#975
b00111 3
16
b00000111 =
#980
06
#985
b01000 3
16
b00001000 =
#990
06
#995
b01001 3
16
b00001001 =
#1000
06
#1005
b01010 3
16
b00001010 =
#1010
06
#1015
b01011 3
16
b00001011 =
#1020
06
#1025
b01100 3
16
b00001100 =
#1030
06
#1035
b01101 3
16
b00001101 =
#1040
06
#1045
b01110 3
16
b00001110 =
#1050
06
#1055
b01111 3
16
b00001111 =
#1060
06
#1065
b10000 3
16
b10101010 =
#1070
06
#1075
b10001 3
14
16
0;
b00000001 =
0>
#1080
b00000 2
b00000 3
06
07
0<
b10101010 =
#1085
16
#1090
06
#1095
16
#1100
06
#1105
16
#1110
06
#1115
16
#1120
06
17
#1125
16
#1130
06
18
b00010001 :
1<
1?
#1135
b00010001 "
b00001 2
04
16
1;
b00010001 =
1>
#1140
06
b00100010 :
#1145
b00100010 #
b00010 2
b00001 3
16
b00100010 =
#1150
06
b00110011 :
#1155
b00110011 $
b00011 2
b00010 3
16
b00110011 =
#1160
06
b01000100 :
#1165
b01000100 %
b00100 2
b00011 3
16
b01000100 =
#1170
06
08
b00000000 :
0?
#1175
b00100 3
14
16
0;
b00000100 =
0>
#1180
b00000 2
b00000 3
06
07
0<
b00010001 =
#1185
16
#1190
06
#1195
16
#1200
06
#1205
16
#1210
06
#1215
16
#1220
06
17
#1225
16
#1230
06
18
1?
#1235
b00000000 "
b00001 2
04
16
1;
b00000000 =
#1240
06
b00000001 :
#1245
b00000001 #
b00010 2
16
#1250
06
b00000010 :
#1255
b00000010 $
b00011 2
16
#1260
06
b00000011 :
#1265
b00000011 %
b00100 2
16
#1270
06
b00000100 :
#1275
b00101 2
16
#1280
06
b00000101 :
#1285
b00110 2
16
#1290
06
b00000110 :
#1295
b00111 2
16
#1300
06
b00000111 :
#1305
b01000 2
16
#1310
06
b00001000 :
#1315
b01001 2
16
#1320
06
b00001001 :
#1325
b01010 2
16
#1330
06
b00001010 :
#1335
b01011 2
16
#1340
06
b00001011 :
#1345
b01100 2
16
#1350
06
b00001100 :
#1355
b01101 2
16
#1360
06
b00001101 :
#1365
b01110 2
16
#1370
06
b00001110 :
#1375
b01111 2
16
#1380
06
b00001111 :
#1385
b10000 2
15
16
09
0?
#1390
06
b11101110 :
#1395
16
#1400
06
08
19
b00000000 :
1<
1>
#1405
b00001 3
05
16
b00000001 =
#1410
06
#1415
b00010 3
16
b00000010 =
#1420
06
#1425
b00011 3
16
b00000011 =
#1430
06
#1435
b00100 3
16
b00000100 =
#1440
06
#1445
b00101 3
16
b00000101 =
#1450
06
#1455
b00110 3
16
b00000110 =
#1460
06
#1465
b00111 3
16
b00000111 =
#1470
06
#1475
b01000 3
16
b00001000 =
#1480
06
#1485
b01001 3
16
b00001001 =
#1490
06
#1495
b01010 3
16
b00001010 =
#1500
06
#1505
b01011 3
16
b00001011 =
#1510
06
#1515
b01100 3
16
b00001100 =
#1520
06
#1525
b01101 3
16
b00001101 =
#1530
06
#1535
b01110 3
16
b00001110 =
#1540
06
#1545
b01111 3
16
b00001111 =
#1550
06
#1555
b10000 3
14
16
0;
b00000000 =
0>
