rtl/common/sync_2ff.sv
// =====================================================================
// sync_2ff.sv  --  Generic N-stage flop synchronizer
// ---------------------------------------------------------------------
// Standard async-input -> safe synchronous output. Default 2 stages,
// which is the textbook MTBF tradeoff for low-frequency async signals
// (PS/2 CLK at <50 kHz, button presses, etc.).
//
// Use:
//   sync_2ff #(.RST_VAL(1'b1)) u_sync (
//       .clk, .rst_n,
//       .async_in (raw_pin),
//       .sync_out (clean)
//   );
//
// RST_VAL is the value the chain takes on async reset; choose to match
// the line's idle-high or idle-low convention so reset doesn't look
// like a fake edge.
// =====================================================================

`ifndef SYNC_2FF_SV
`define SYNC_2FF_SV

module sync_2ff #(
    parameter int   N_STAGES = 2,
    parameter logic RST_VAL  = 1'b0
) (
    input  logic clk,
    input  logic rst_n,
    input  logic async_in,
    output logic sync_out
);

    // SYNCASYNCNET fires when this primitive is used as a reset
    // synchroniser (async_in tied to 1'b1 with the async reset port
    // driving the actual reset signal). That is the textbook reset-
    // sync pattern -- the warning is informational, not a bug.
    /* verilator lint_off SYNCASYNCNET */
    logic [N_STAGES-1:0] sync_q;

    always_ff @(posedge clk or negedge rst_n) begin
        if (!rst_n) sync_q <= {N_STAGES{RST_VAL}};
        else        sync_q <= {sync_q[N_STAGES-2:0], async_in};
    end
    /* verilator lint_on SYNCASYNCNET */

    assign sync_out = sync_q[N_STAGES-1];

endmodule

`endif  // SYNC_2FF_SV

sim/waves/sync_2ff.vcd
$version Generated by VerilatedVcd $end
$timescale 1ps $end
 $scope module TOP $end
  $var wire 1 " clk $end
  $var wire 1 # rst_n $end
  $var wire 1 $ async_in $end
  $var wire 1 % sync_out $end
  $scope module sync_2ff $end
   $var wire 32 ' N_STAGES [31:0] $end
   $var wire 1 ( RST_VAL $end
   $var wire 1 " clk $end
   $var wire 1 # rst_n $end
   $var wire 1 $ async_in $end
   $var wire 1 % sync_out $end
   $var wire 2 & sync_q [1:0] $end
  $upscope $end
 $upscope $end
$enddefinitions $end


#0
0"
0#
0$
0%
b00 &
b00000000000000000000000000000010 '
0(
#5
1"
#10
0"
#15
1"
#20
0"
#25
1"
#30
0"
#35
1"
#40
0"
1$
#45
1"
#50
0"
#55
1"
#60
0"
#65
1"
#70
0"
#75
1"
#80
0"
0$
#85
1"
#90
0"
#95
1"
#100
0"
#105
1"
#110
0"
#115
1"
#120
0"
1#
1$
#125
1"
b01 &
#130
0"
#135
1"
1%
b11 &
#140
0"
0#
0$
0%
b00 &
#145
1"
#150
0"
#155
1"
#160
0"
#165
1"
#170
0"
#175
1"
#180
0"
1#
1$
#185
1"
b01 &
#190
0"
0$
#195
1"
1%
b10 &
#200
0"
#205
1"
0%
b00 &
#210
0"
0#
#215
1"
#220
0"
#225
1"
#230
0"
#235
1"
#240
0"
#245
1"
#250
0"
1#
1$
#255
1"
b01 &
#260
0"
0$
#265
1"
1%
b10 &
#270
0"
1$
#275
1"
0%
b01 &
#280
0"
0$
#285
1"
1%
b10 &
#290
0"
1$
#295
1"
0%
b01 &
#300
0"
0$
#305
1"
1%
b10 &
